LICENSE
MANIFEST.in
README.rst
setup.py
src/ofxstatement/__init__.py
src/ofxstatement/plugins/__init__.py
src/ofxstatement/plugins/easybank.py
src/ofxstatement/plugins/ingdiba.py
src/ofxstatement/plugins/livebank.py
src/ofxstatement/plugins/oberbank.py
src/ofxstatement/plugins/raiffeisen.py
src/ofxstatement/plugins/utils.py
src/ofxstatement/plugins/tests/__init__.py
src/ofxstatement/plugins/tests/test_easybank.py
src/ofxstatement/plugins/tests/test_ingdiba.py
src/ofxstatement/plugins/tests/test_livebank.py
src/ofxstatement/plugins/tests/test_oberbank.py
src/ofxstatement/plugins/tests/test_raiffeisen.py
src/ofxstatement/plugins/tests/test_utils.py
src/ofxstatement_austrian.egg-info/PKG-INFO
src/ofxstatement_austrian.egg-info/SOURCES.txt
src/ofxstatement_austrian.egg-info/dependency_links.txt
src/ofxstatement_austrian.egg-info/entry_points.txt
src/ofxstatement_austrian.egg-info/namespace_packages.txt
src/ofxstatement_austrian.egg-info/requires.txt
src/ofxstatement_austrian.egg-info/top_level.txt
src/ofxstatement_austrian.egg-info/zip-safe