Metadata-Version: 1.1
Name: ofxstatement-austrian
Version: 0.0.4
Summary: Statement parser for several austrian banks
Home-page: https://github.com/nblock/ofxstatement-austrian
Author: Florian Preinstorfer
Author-email: nblock@archlinux.us
License: GPLv3
Keywords: ofxstatement,easybank,ing-diba,livebank,raiffeisen,oberbank
Platform: UNKNOWN
Classifier: Development Status :: 3 - Alpha
Classifier: Programming Language :: Python :: 3
Classifier: Programming Language :: Python :: 3.2
Classifier: Programming Language :: Python :: 3.3
Classifier: Programming Language :: Python :: 3.4
Classifier: Programming Language :: Python :: 3.5
Classifier: Natural Language :: English
Classifier: Topic :: Office/Business :: Financial :: Accounting
Classifier: Topic :: Utilities
Classifier: Environment :: Console
Classifier: Operating System :: OS Independent
Classifier: License :: OSI Approved :: GNU General Public License v3 (GPLv3)
